ytscraper/__init__.py
ytscraper/__main__.py
ytscraper/app.py
ytscraper/commands/config.py
ytscraper/commands/search.py
ytscraper/helper/configfile.py
ytscraper/helper/echo.py
ytscraper/helper/export.py
ytscraper/helper/yt_api.py
yt_scraper-0.8.4.dist-info/entry_points.txt
yt_scraper-0.8.4.dist-info/WHEEL
yt_scraper-0.8.4.dist-info/METADATA
yt_scraper-0.8.4.dist-info/RECORD
