Metadata-Version: 2.1
Name: yt-scraper
Version: 0.8.4
Summary: Command line utility querying the YouTube API v3.
License: Unlicense
Keywords: youtube,scraping,API
Author: Michael Brauweiler
Author-email: rattletat@posteo.me
Requires-Python: >=3.8,<4.0
Classifier: License :: Other/Proprietary License
Classifier: Programming Language :: Python :: 3
Classifier: Programming Language :: Python :: 3.8
Requires-Dist: appdirs (>=1.4.3,<2.0.0)
Requires-Dist: click (>=7.1.1,<8.0.0)
Requires-Dist: google-api-python-client (>=1.8.0,<2.0.0)
Requires-Dist: ratelimit (>=2.2.1,<3.0.0)
Requires-Dist: toml (>=0.10.0,<0.11.0)
